genDocsGPT/__init__.py
genDocsGPT/__main__.py
utils/__init__.py
utils/build_prompt.py
utils/check_params.py
utils/gen_docs.py
utils/get_token.py
utils/help.py
utils/read_files.py
utils/write_doc.py
utils/tests/__init__.py
utils/tests/build_prompt_test.py
utils/tests/check_params_test.py
utils/tests/get_token_test.py
utils/tests/read_files_test.py
utils/tests/write_doc_test.py
genDocsGPT-1.0b17.dist-info/LICENSE
genDocsGPT-1.0b17.dist-info/METADATA
genDocsGPT-1.0b17.dist-info/WHEEL
genDocsGPT-1.0b17.dist-info/entry_points.txt
genDocsGPT-1.0b17.dist-info/top_level.txt
genDocsGPT-1.0b17.dist-info/RECORD
