Metadata-Version: 2.1
Name: genDocsGPT
Version: 1.0b17
Summary: Generate API documentation in MarkDown based on the models and api handlers for given project using ChatGPT.
Home-page: https://github.com/marco-rosner/genDocsGPT
Author: Marco Rosner
Author-email: marco.rosner@gmail.com
License: MIT
Project-URL: Bug Tracker, https://github.com/marco-rosner/genDocsGPT/issues
Project-URL: repository, https://github.com/marco-rosner/genDocsGPT
Keywords: generator,documentation,GPT,ChatGPT,genDocsGPT,OpenAI
Classifier: Development Status :: 4 - Beta
Classifier: Environment :: Console
Classifier: Intended Audience :: Developers
Classifier: Intended Audience :: Information Technology
Classifier: License :: OSI Approved :: MIT License
Classifier: Operating System :: OS Independent
Classifier: Programming Language :: Python :: 3
Classifier: Topic :: Documentation
Classifier: Topic :: Software Development :: Documentation
Classifier: Topic :: Utilities
Requires-Python: >=3.7
License-File: LICENSE
Requires-Dist: openai ==0.28.0
Requires-Dist: pytest ==7.4.2
